[{
  "data": {
    "heading": "E",
    "men": 7,
    "contracts": [
      {
        "amount": 100,
        "resource": "QUARTZ"
      },
      {
        "amount": 4000,
        "resource": "WOOD"
      }
    ],
    "budget": 20000
  },
  "part": "Engine",
  "time": 1526500331273,
  "meth": "initialize"
},{
  "data": {"action": "stop"},
  "part": "Explorer",
  "time": 1526500331273,
  "meth": "takeDecision"
},{
  "data": {
    "cost": 5,
    "extras": {},
    "status": "OK"
  },
  "part": "Engine",
  "time": 1526500331273,
  "meth": "takeDecision"
}]